template_analyzer/__init__.py
template_analyzer/djangoanalyzer.py
template_analyzer/models.py
template_analyzer/templatetags/__init__.py
template_analyzer/templatetags/template_analyzer_test_tags.py
template_analyzer/tests/__init__.py
template_analyzer/tests/app_loader.py
template_analyzer/tests/test_placeholder.py
django_template_analyzer-2.1.dist-info/AUTHORS
django_template_analyzer-2.1.dist-info/LICENSE
django_template_analyzer-2.1.dist-info/METADATA
django_template_analyzer-2.1.dist-info/WHEEL
django_template_analyzer-2.1.dist-info/top_level.txt
django_template_analyzer-2.1.dist-info/RECORD
