Metadata-Version: 2.1
Name: django-template-analyzer
Version: 2.1
Summary: Django Template Analyzer - Extract template nodes from a Django template
Home-page: https://github.com/edoburu/django-template-analyzer
Download-URL: https://github.com/edoburu/django-template-analyzer/zipball/master
Author: Diederik van der Boor & Django CMS developers
Author-email: opensource@edoburu.nl
License: BSD License
Platform: OS Independent
Classifier: Development Status :: 5 - Production/Stable
Classifier: Environment :: Web Environment
Classifier: Intended Audience :: Developers
Classifier: License :: OSI Approved :: BSD License
Classifier: Operating System :: OS Independent
Classifier: Programming Language :: Python
Classifier: Programming Language :: Python :: 3
Classifier: Programming Language :: Python :: 3.5
Classifier: Programming Language :: Python :: 3.6
Classifier: Programming Language :: Python :: 3.7
Classifier: Programming Language :: Python :: 3.8
Classifier: Programming Language :: Python :: 3.9
Classifier: Framework :: Django
Classifier: Framework :: Django :: 1.8
Classifier: Framework :: Django :: 1.9
Classifier: Framework :: Django :: 1.10
Classifier: Framework :: Django :: 1.11
Classifier: Framework :: Django :: 2.0
Classifier: Framework :: Django :: 2.1
Classifier: Framework :: Django :: 2.2
Classifier: Framework :: Django :: 3.0
Classifier: Framework :: Django :: 3.1
Classifier: Framework :: Django :: 3.2
Classifier: Framework :: Django :: 4.0
Classifier: Topic :: Software Development
Classifier: Topic :: Software Development :: Libraries :: Application Frameworks
Classifier: Topic :: Software Development :: Libraries :: Python Modules
License-File: LICENSE
License-File: AUTHORS
